yowasp_nextpnr_nexus/__init__.py
yowasp_nextpnr_nexus/nextpnr-nexus.wasm
yowasp_nextpnr_nexus/prjoxide.wasm
yowasp_nextpnr_nexus/share/nexus/chipdb-LIFCL.bin
yowasp_nextpnr_nexus-0.9.0.0.post686.dist-info/METADATA
yowasp_nextpnr_nexus-0.9.0.0.post686.dist-info/WHEEL
yowasp_nextpnr_nexus-0.9.0.0.post686.dist-info/entry_points.txt
yowasp_nextpnr_nexus-0.9.0.0.post686.dist-info/top_level.txt
yowasp_nextpnr_nexus-0.9.0.0.post686.dist-info/RECORD
